trading_sdk/__init__.py
trading_sdk/client.py
trading_sdk/example_usage.py
trading_sdk/exceptions.py
ixlab_tradingSDK-1.0.0.dist-info/LICENSE
ixlab_tradingSDK-1.0.0.dist-info/METADATA
ixlab_tradingSDK-1.0.0.dist-info/WHEEL
ixlab_tradingSDK-1.0.0.dist-info/top_level.txt
ixlab_tradingSDK-1.0.0.dist-info/RECORD
