Metadata-Version: 2.1
Name: ixlab-tradingSDK
Version: 1.0.0
Summary: A Python SDK for interacting with the iX LAB trading API
Home-page: https://github.com/iX-LAB-Official/trading_sdk
Author: iX LAB
Author-email: info@ixlab.ai
License: MIT
Platform: UNKNOWN
Classifier: Programming Language :: Python :: 3
Classifier: Operating System :: OS Independent
Requires-Dist: aiohttp (>=3.7.4)
